{
    "base": "castle",
    "name": "Castle",
    "stage": 0,
    "dependencies": [],
    "children": [
        {
            "base": "castle",
            "stage": 1,
            "name": "Castle 1",
            "dependencies": [{ "base": "castle", "stage": 0 }],
            "children": [
                {
                    "base": "castle",
                    "stage": 2,
                    "name": "Castle 2",
                    "dependencies": [{ "base": "castle", "stage": 1 }],
                    "children": [
                        {
                            "base": "castle",
                            "stage": 3,
                            "name": "Castle 3",
                            "dependencies": [
                                { "base": "castle", "stage": 2 },
                                { "base": "rock", "stage": 1 }
                            ],
                            "children": []
                        }
                    ]
                }
            ]
        }
    ]
}